djangocms_admindocs_style/__init__.py
djangocms_admindocs_style/cms_toolbars.py
djangocms_admindocs_style/models.py
djangocms_admindocs_style/static/djangocms_admindocs_style/css/djangocms-admindocs.css
djangocms_admindocs_style/templates/admin/base_admin_docs.html
djangocms_admindocs_style/templates/admin/inc/branding.html
djangocms_admindocs_style/templates/admin_doc/bookmarklets.html
djangocms_admindocs_style/templates/admin_doc/index.html
djangocms_admindocs_style/templates/admin_doc/missing_docutils.html
djangocms_admindocs_style/templates/admin_doc/model_detail.html
djangocms_admindocs_style/templates/admin_doc/model_index.html
djangocms_admindocs_style/templates/admin_doc/template_detail.html
djangocms_admindocs_style/templates/admin_doc/template_filter_index.html
djangocms_admindocs_style/templates/admin_doc/template_tag_index.html
djangocms_admindocs_style/templates/admin_doc/view_detail.html
djangocms_admindocs_style/templates/admin_doc/view_index.html
djangocms_admindocs_style/templates/djangocms_admindocs_style/base.html
djangocms_admindocs_style-0.2.0.dist-info/DESCRIPTION.rst
djangocms_admindocs_style-0.2.0.dist-info/METADATA
djangocms_admindocs_style-0.2.0.dist-info/metadata.json
djangocms_admindocs_style-0.2.0.dist-info/RECORD
djangocms_admindocs_style-0.2.0.dist-info/top_level.txt
djangocms_admindocs_style-0.2.0.dist-info/WHEEL
