Metadata-Version: 2.0
Name: djangocms-admindocs-style
Version: 0.2.0
Summary: Adds DjangoCMS Admin Styles to the admindocs
Home-page: https://github.com/goldhand/djangocms-admindocs-style
Author: Will Farley
Author-email: willf@hzdg.com
License: BSD
Keywords: djangocms-admindocs-style
Platform: UNKNOWN
Classifier: Development Status :: 3 - Alpha
Classifier: Framework :: Django
Classifier: Framework :: Django :: 1.8
Classifier: Framework :: Django :: 1.9
Classifier: Intended Audience :: Developers
Classifier: License :: OSI Approved :: BSD License
Classifier: Natural Language :: English
Classifier: Programming Language :: Python :: 2
Classifier: Programming Language :: Python :: 2.7
Classifier: Programming Language :: Python :: 3
Classifier: Programming Language :: Python :: 3.3
Classifier: Programming Language :: Python :: 3.4
Classifier: Programming Language :: Python :: 3.5
Requires-Dist: django
Requires-Dist: djangocms-admin-style
